MANIFEST.in
README.md
README.md.in
setup.cfg
setup.py
examples/two_step.py
marx/__init__.py
marx/workflow/__init__.py
marx/workflow/context.py
marx/workflow/exceptions.py
marx/workflow/flow.py
marx/workflow/step.py
marx_workflows.egg-info/PKG-INFO
marx_workflows.egg-info/SOURCES.txt
marx_workflows.egg-info/dependency_links.txt
marx_workflows.egg-info/top_level.txt
tests/__init__.py
tests/__init__.pyc
tests/test_init.py
tests/test_init.pyc
tests/workflow/__init__.py
tests/workflow/__init__.pyc
tests/workflow/example_1.py
tests/workflow/example_1.pyc
tests/workflow/example_objects.py
tests/workflow/example_objects.pyc
tests/workflow/test_context.py
tests/workflow/test_context.pyc
tests/workflow/test_flow.py
tests/workflow/test_flow.pyc
tests/workflow/test_step.py
tests/workflow/test_step.pyc