Metadata-Version: 1.1
Name: marx-workflows
Version: 0.0.8
Summary: marx
Home-page: https://github.com/ninowalker/marx
Author: Nino Walker
Author-email: nino.walker@gmail.com
License: BSD
Platform: UNKNOWN
Classifier: License :: OSI Approved :: BSD License
